README
main.py
setup.cfg
setup.py
CryptoIM.egg-info/PKG-INFO
CryptoIM.egg-info/SOURCES.txt
CryptoIM.egg-info/dependency_links.txt
CryptoIM.egg-info/requires.txt
CryptoIM.egg-info/top_level.txt
cryptoim/__init__.py
cryptoim/cli.py
cryptoim/common.py
cryptoim/const.py
cryptoim/decryptor_core.py
cryptoim/encryptor_core.py
cryptoim/key_exchange.py
cryptoim/xmpp.py
tests/integration/TestCli.py
tests/integration/TestXMPP.py
tests/integration/__init__.py
tests/unit/TestDecryptorCore.py
tests/unit/TestEncryptDecrypt.py
tests/unit/TestEncryptorCore.py
tests/unit/TestKeyExchange.py
tests/unit/__init__.py
tests/unit/common.py