Metadata-Version: 1.1
Name: CryptoIM
Version: 0.1.1
Summary: Crypto Instant Messenger
Home-page: http://pypi.python.org/pypi/CryptoIM/
Author: CryptoIM Development Team
Author-email: skopekondrej@gmail.com
License: Apache License 2.0
Keywords: crypto instant messenger
Platform: UNKNOWN
Classifier: Development Status :: 4 - Beta
Classifier: Environment :: Console
Classifier: License :: OSI Approved :: Apache Software License
Classifier: Natural Language :: English
Classifier: Programming Language :: Python
Classifier: Topic :: Communications :: Chat
Classifier: Topic :: Security :: Cryptography
